CMakeLists.txt
MANIFEST.in
README.rst
setup.py
scripts/foamreconstr
src/foamgen/__init__.py
src/foamgen/generation.py
src/foamgen/geo_tools.py
src/foamgen/morphology.py
src/foamgen/packing.py
src/foamgen/smesh.py
src/foamgen/tessellation.py
src/foamgen/umesh.py
src/foamgen/vtk_tools.py
src/foamgen.egg-info/PKG-INFO
src/foamgen.egg-info/SOURCES.txt
src/foamgen.egg-info/dependency_links.txt
src/foamgen.egg-info/entry_points.txt
src/foamgen.egg-info/not-zip-safe
src/foamgen.egg-info/requires.txt
src/foamgen.egg-info/top_level.txt
src/foamgen/cxx/allocation.cc
src/foamgen/cxx/allocation.hh
src/foamgen/cxx/determinant.cc
src/foamgen/cxx/determinant.hh
src/foamgen/cxx/edges.cc
src/foamgen/cxx/edges.hh
src/foamgen/cxx/foams.cc
src/foamgen/cxx/geometry.cc
src/foamgen/cxx/geometry.hh
src/foamgen/cxx/globals.cc
src/foamgen/cxx/globals.hh
src/foamgen/cxx/inout.cc
src/foamgen/cxx/inout.hh
src/foamgen/cxx/nodes.cc
src/foamgen/cxx/nodes.hh
src/foamgen/cxx/seeds.cc
src/foamgen/cxx/seeds.hh
src/foamgen/cxx/skeleton.cc
src/foamgen/cxx/skeleton.hh
src/foamgen/cxx/struts.cc
src/foamgen/cxx/struts.hh
src/foamgen/cxx/walls.cc
src/foamgen/cxx/walls.hh