Metadata-Version: 2.1
Name: foamgen
Version: 0.2.0
Summary: Generate virtual closed-cell or open-cell foam structure.
Home-page: https://github.com/japaf/foamgen
Author: Pavel Ferkl
Author-email: pavel.ferkl@gmail.com
License: UNKNOWN
Keywords: foam generation reconstruction morphology
Platform: UNKNOWN
Classifier: Intended Audience :: Science/Research
Classifier: Development Status :: 2 - Pre-Alpha
Classifier: Programming Language :: Python :: 3 :: Only
Classifier: Programming Language :: C++
Classifier: License :: OSI Approved :: MIT License
Classifier: Operating System :: OS Independent
Classifier: Topic :: Scientific/Engineering
